qlient/__init__.py
qlient/builder.py
qlient/cache.py
qlient/cli.py
qlient/client.py
qlient/helpers.py
qlient/loaders.py
qlient/logger.py
qlient/proxy.py
qlient/schema.py
qlient/settings.py
qlient/transport.py
qlient/utils.py
python_qlient-1.2.2.dist-info/LICENSE
python_qlient-1.2.2.dist-info/METADATA
python_qlient-1.2.2.dist-info/WHEEL
python_qlient-1.2.2.dist-info/entry_points.txt
python_qlient-1.2.2.dist-info/top_level.txt
python_qlient-1.2.2.dist-info/RECORD
