Metadata-Version: 2.1
Name: python-qlient
Version: 1.2.2
Summary: A fast and modern graphql client library designed with simplicity in mind.
Home-page: https://github.com/Lab9/python-qlient
Author: Daniel Seifert
Author-email: info@danielseifert.ch
License: MIT
Keywords: python graphql client api async asyncio graph requests query mutation subscription
Platform: UNKNOWN
Classifier: Development Status :: 5 - Production/Stable
Classifier: License :: OSI Approved :: MIT License
Classifier: Programming Language :: Python :: 3
Classifier: Programming Language :: Python :: 3.7
Classifier: Framework :: AsyncIO
Classifier: Natural Language :: English
Requires-Dist: requests (==2.*)
Requires-Dist: websockets (==8.1)
